HtmlTestRunner/__init__.py
HtmlTestRunner/result.py
HtmlTestRunner/runner.py
HtmlTestRunner/template/report_template.html
html_testRunner-1.2.dist-info/AUTHORS.md
html_testRunner-1.2.dist-info/LICENSE
html_testRunner-1.2.dist-info/METADATA
html_testRunner-1.2.dist-info/WHEEL
html_testRunner-1.2.dist-info/top_level.txt
html_testRunner-1.2.dist-info/RECORD
