Metadata-Version: 1.1
Name: html-testRunner
Version: 1.2
Summary: A Test Runner in python, for Human Readable HTML Reports
Home-page: https://github.com/oldani/HtmlTestRunner
Author: Ordanis Sanchez Suero
Author-email: ordanisanchez@gmail.com
License: MIT license
Keywords: HtmlTestRunner TestRunner Html Reports
Platform: UNKNOWN
Classifier: Development Status :: 4 - Beta
Classifier: Intended Audience :: Developers
Classifier: License :: OSI Approved :: MIT License
Classifier: Natural Language :: English
Classifier: Programming Language :: Python :: 3.5
